backpy/__init__.py
backpy/__main__.py
backpy-0.0.0.data/scripts/backpy
backpy-0.0.0.dist-info/METADATA
backpy-0.0.0.dist-info/WHEEL
backpy-0.0.0.dist-info/top_level.txt
backpy-0.0.0.dist-info/RECORD
