Metadata-Version: 2.1
Name: backpy
Version: 0.0.0
Summary: A Python interface to interact with gmail. 
Home-page: https://pypi.org/project/emailpy
Author: Sandra Mattar
Author-email: sandrawmattar1@gmail.com
License: UNKNOWN
Platform: UNKNOWN
